callstack.py
callstack-0.2.0.dist-info/WHEEL
callstack-0.2.0.dist-info/METADATA
callstack-0.2.0.dist-info/RECORD
