Metadata-Version: 2.1
Name: callstack
Version: 0.2.0
Summary: A call stack which includes the Class, and a simpler Frame structure.
Author-email: Jonathan Woodburn <atriace@gmail.com>
Requires-Python: >=3.8
Classifier: Programming Language :: Python :: 3
Classifier: License :: OSI Approved :: Apache Software License
Classifier: Operating System :: OS Independent
Project-URL: Homepage, https://gitlab.com/Atriace/callstack
Project-URL: Issues, https://gitlab.com/Atriace/callstack/-/issues
